streamlit_lexical_extended/__init__.py
streamlit_lexical_extended/dialog_two_editors.py
streamlit_lexical_extended/example.py
streamlit_lexical_extended/example2.py
streamlit_lexical_extended/test_formatting.py
streamlit_lexical_extended/test_table_menu.py
streamlit_lexical_extended/frontend/build/asset-manifest.json
streamlit_lexical_extended/frontend/build/bootstrap.min.css
streamlit_lexical_extended/frontend/build/index.html
streamlit_lexical_extended/frontend/build/static/css/main.52419a26.css
streamlit_lexical_extended/frontend/build/static/css/main.52419a26.css.map
streamlit_lexical_extended/frontend/build/static/js/main.c789150f.js
streamlit_lexical_extended/frontend/build/static/js/main.c789150f.js.LICENSE.txt
streamlit_lexical_extended/frontend/build/static/js/main.c789150f.js.map
streamlit_lexical_extended/frontend/build/static/media/arrow-clockwise.2ba775456dd603357519.svg
streamlit_lexical_extended/frontend/build/static/media/arrow-counterclockwise.48745dc8e6d9b1a2f8ec.svg
streamlit_lexical_extended/frontend/build/static/media/list-ol.14fef2e6f0e79b263d06.svg
streamlit_lexical_extended/frontend/build/static/media/list-ul.06392a7729ef11b23ab1.svg
streamlit_lexical_extended/frontend/build/static/media/quote.a67ec1269d94bdab75dd.svg
streamlit_lexical_extended/frontend/build/static/media/table.a7ea9d9cc6d77a9597e5.svg
streamlit_lexical_extended/frontend/build/static/media/type-bold.b3bec3f33045771f9484.svg
streamlit_lexical_extended/frontend/build/static/media/type-italic.d3971b39b0fe39a09b1b.svg
streamlit_lexical_extended/frontend/build/static/media/type-strikethrough.5d23c9047ed5de3d800c.svg
streamlit_lexical_extended/frontend/build/static/media/type-underline.b41f84ace38d530f30b9.svg
streamlit_lexical_extended-0.2.1.dist-info/licenses/LICENSE
streamlit_lexical_extended-0.2.1.dist-info/METADATA
streamlit_lexical_extended-0.2.1.dist-info/WHEEL
streamlit_lexical_extended-0.2.1.dist-info/top_level.txt
streamlit_lexical_extended-0.2.1.dist-info/RECORD
